gwdama/__init__.py
gwdama/io/__init__.py
gwdama/io/customLogger.py
gwdama/io/dataset.py
gwdama/io/ffl_paths.py
gwdama/io/gwLogger.py
gwdama/io/gwdatamanager.py
gwdama/plot/__init__.py
gwdama/plot/plot.py
gwdama/preprocessing/__init__.py
gwdama/preprocessing/preprocessing.py
gwdama/utilities/__init__.py
gwdama/utilities/utilities.py
gwdama-0.6.0.dist-info/licenses/LICENSE
gwdama-0.6.0.dist-info/METADATA
gwdama-0.6.0.dist-info/WHEEL
gwdama-0.6.0.dist-info/top_level.txt
gwdama-0.6.0.dist-info/RECORD
