Metadata-Version: 2.4
Name: gwdama
Version: 0.6.0
Summary: A GW data manager package and more
Author-email: Pisa Detchar Group <francesco.direnzo@df.unipi.it>
License: MIT
Project-URL: Homepage, https://gwnoisehunt.gitlab.io/gwdama
Project-URL: Source, https://gitlab.com/gwnoisehunt/gwdama
Classifier: Programming Language :: Python :: 3
Classifier: Programming Language :: Python :: 3 :: Only
Classifier: Programming Language :: Python :: 3.9
Classifier: Programming Language :: Python :: 3.10
Classifier: Programming Language :: Python :: 3.11
Classifier: Programming Language :: Python :: 3.12
Classifier: License :: OSI Approved :: MIT License
Classifier: Operating System :: OS Independent
Requires-Python: <3.13,>=3.9
License-File: LICENSE
Requires-Dist: gwdatafind
Requires-Dist: gwpy>=3.0
Requires-Dist: gwosc>=0.6
Requires-Dist: h5py>=3.10
Requires-Dist: lalsuite>=6.73
Requires-Dist: matplotlib>=3.8
Requires-Dist: numpy>=1.26
Requires-Dist: pandas>=2.1
Requires-Dist: python-dateutil
Requires-Dist: scikit-learn>=1.4
Requires-Dist: scipy>=1.12
Requires-Dist: six>=1.5
Requires-Dist: astropy>=6.0; python_version >= "3.10"
Requires-Dist: astropy<6,>=5.3; python_version < "3.10"
Provides-Extra: dev
Requires-Dist: pytest>=7.0; extra == "dev"
Requires-Dist: pytest-cov>=4.0; extra == "dev"
Requires-Dist: build>=1.0; extra == "dev"
Requires-Dist: twine>=4.0; extra == "dev"
Requires-Dist: ruff>=0.4; extra == "dev"
Requires-Dist: pre-commit>=3.0; extra == "dev"
Requires-Dist: sphinx>=7.2; extra == "dev"
Requires-Dist: sphinx-rtd-theme>=2.0; extra == "dev"
Requires-Dist: sphinxcontrib-napoleon>=0.7; extra == "dev"
Requires-Dist: jupyter>=1.0; extra == "dev"
Provides-Extra: docs
Requires-Dist: sphinx>=7.2; extra == "docs"
Requires-Dist: sphinx-rtd-theme>=2.0; extra == "docs"
Requires-Dist: sphinxcontrib-napoleon>=0.7; extra == "docs"
Provides-Extra: gui
Requires-Dist: pyqt5; extra == "gui"
Dynamic: license-file
